todolist/LICENSE
todolist/__init__.py
todolist/__main__.py
todolist/advWidgets.py
todolist/todolistdb.py
todolist-0.6.0.dist-info/METADATA
todolist-0.6.0.dist-info/RECORD
todolist-0.6.0.dist-info/WHEEL
todolist-0.6.0.dist-info/entry_points.txt
todolist-0.6.0.dist-info/top_level.txt
