Metadata-Version: 2.1
Name: todolist
Version: 0.6.0
Summary: The Open Source CLI To Do List App
Home-page: https://github.com/StillnessFate/Open-Source-ToDo-List
Author: Kang MinSeok
Author-email: stillnessfate@gmail.com
License: MIT License
Download-URL: https://github.com/StillnessFate/Open-Source-ToDo-List/archive/master.tar.gz
Keywords: todo list,task manager
Platform: UNKNOWN
Classifier: Programming Language :: Python :: 3
Classifier: Programming Language :: Python :: 3.2
Classifier: Programming Language :: Python :: 3.3
Classifier: Programming Language :: Python :: 3.4
Classifier: Programming Language :: Python :: 3.5
Classifier: Programming Language :: Python :: 3.6
Requires-Python: >=3
Requires-Dist: asciimatics (==1.9.0)
